Apache-License-2.0.txt
LICENSE
MANIFEST.in
OFL-License.txt
README.rst
requirements.txt
setup.py
ushahidi_sphinx_rtd_theme/__init__.py
ushahidi_sphinx_rtd_theme/breadcrumbs.html
ushahidi_sphinx_rtd_theme/footer.html
ushahidi_sphinx_rtd_theme/layout.html
ushahidi_sphinx_rtd_theme/layout_old.html
ushahidi_sphinx_rtd_theme/search.html
ushahidi_sphinx_rtd_theme/searchbox.html
ushahidi_sphinx_rtd_theme/theme.conf
ushahidi_sphinx_rtd_theme/versions.html
ushahidi_sphinx_rtd_theme.egg-info/PKG-INFO
ushahidi_sphinx_rtd_theme.egg-info/SOURCES.txt
ushahidi_sphinx_rtd_theme.egg-info/dependency_links.txt
ushahidi_sphinx_rtd_theme.egg-info/not-zip-safe
ushahidi_sphinx_rtd_theme.egg-info/requires.txt
ushahidi_sphinx_rtd_theme.egg-info/top_level.txt
ushahidi_sphinx_rtd_theme/static/ushahidi.css
ushahidi_sphinx_rtd_theme/static/css/badge_only.css
ushahidi_sphinx_rtd_theme/static/css/theme.css
ushahidi_sphinx_rtd_theme/static/fonts/Inconsolata-Bold.ttf
ushahidi_sphinx_rtd_theme/static/fonts/Inconsolata-Regular.ttf
ushahidi_sphinx_rtd_theme/static/fonts/Lato-Bold.ttf
ushahidi_sphinx_rtd_theme/static/fonts/Lato-Regular.ttf
ushahidi_sphinx_rtd_theme/static/fonts/RobotoSlab-Bold.ttf
ushahidi_sphinx_rtd_theme/static/fonts/RobotoSlab-Regular.ttf
ushahidi_sphinx_rtd_theme/static/fonts/fontawesome-webfont.eot
ushahidi_sphinx_rtd_theme/static/fonts/fontawesome-webfont.svg
ushahidi_sphinx_rtd_theme/static/fonts/fontawesome-webfont.ttf
ushahidi_sphinx_rtd_theme/static/fonts/fontawesome-webfont.woff
ushahidi_sphinx_rtd_theme/static/js/modernizr.min.js
ushahidi_sphinx_rtd_theme/static/js/theme.js