Metadata-Version: 1.1
Name: ushahidi-sphinx-rtd-theme
Version: 0.1.8.1
Summary: Ushahidi customisation of ReadTheDocs.org theme for Sphinx, 2015 version.
Home-page: https://github.com/snide/ushahidi_sphinx_rtd_theme/
Author: Dave Snider, Will Doran
Author-email: dave.snider@gmail.com, will@ushahidi.com
License: MIT
Platform: UNKNOWN
Classifier: Development Status :: 3 - Alpha
Classifier: License :: OSI Approved :: BSD License
Classifier: Environment :: Console
Classifier: Environment :: Web Environment
Classifier: Intended Audience :: Developers
Classifier: Programming Language :: Python :: 2.7
Classifier: Programming Language :: Python :: 3
Classifier: Operating System :: OS Independent
Classifier: Topic :: Documentation
Classifier: Topic :: Software Development :: Documentation
